processdat.py
processdat-0.0.1.dist-info/LICENSE.txt
processdat-0.0.1.dist-info/METADATA
processdat-0.0.1.dist-info/WHEEL
processdat-0.0.1.dist-info/top_level.txt
processdat-0.0.1.dist-info/RECORD
