Metadata-Version: 2.1
Name: processdat
Version: 0.0.1
Summary: Data preprocessing for ML, returns X_train, X_test, y_train, y_test
Home-page: https://github.com/ShayanBanerjee/processdat.git
Author: Shayan Banerjee
Author-email: shayanbanerjee96@gmail.com
License: UNKNOWN
Platform: UNKNOWN
Classifier: Programming Language :: Python :: 3
Classifier: Programming Language :: Python :: 3.6
Classifier: Programming Language :: Python :: 3.7
Classifier: License :: OSI Approved :: MIT License
Classifier: Operating System :: OS Independent
Requires-Dist: numpy (>=1.19.2)
Requires-Dist: pandas (>=1.1.3)
Requires-Dist: scikit-learn (>=0.22.0)
